{
  "items": [
    {
      "issueTitle": "옥주현",
      "issueKey": "옥주현",
      "title": "옥주현",
      "representativeTitle": "옥주현, 한남더힐 100평집 190억원에 매입 “생애 첫 내집”"
    },
    {
      "issueTitle": "김민경",
      "issueKey": "김민경",
      "title": "김민경",
      "representativeTitle": "‘45세’ 미코 출신 김민경 임신 소식… “이 나이에 임밍아웃”"
    },
    {
      "issueTitle": "피아노맨",
      "issueKey": "피아노맨",
      "title": "피아노맨",
      "representativeTitle": "피아노맨, 오늘 '2년 교제' 비연예인과 결혼"
    },
    {
      "issueTitle": "조명우",
      "issueKey": "조명우",
      "title": "조명우",
      "representativeTitle": "‘세계1위’ 조명우 보고타3쿠션월드컵 악연 끊었다…타이홍치엠 꺾고 4강 진출, 타스데미르와 결승行 다퉈"
    },
    {
      "issueTitle": "신동엽",
      "issueKey": "신동엽",
      "title": "신동엽",
      "representativeTitle": "신동엽, 이경실·조혜련에 고급 도시락 플렉스 “옛날에 밥 많이 얻어먹어”"
    },
    {
      "issueTitle": "전유진",
      "issueKey": "전유진",
      "title": "전유진",
      "representativeTitle": "'트롯퀸' 전유진, '전국노래자랑' 경북 의성군 편 축하공연"
    },
    {
      "issueTitle": "박성한",
      "issueKey": "박성한",
      "title": "박성한",
      "representativeTitle": "[포토] 3타수 3안타 박성한, 뜨겁다 뜨거워"
    },
    {
      "issueTitle": "변우석",
      "issueKey": "변우석",
      "title": "변우석",
      "representativeTitle": "모델료 20만원서 수십억 몸값으로…변우석이 증명한 ‘가장 비싼 영수증’"
    },
    {
      "issueTitle": "모든 선박",
      "issueKey": "모든 선박",
      "title": "모든 선박",
      "representativeTitle": "[속보] 카타르 , 12일 부터 모든 선박의 완전한 항해 재개 선언… 종류 불문"
    }
  ],
  "history": [
    {
      "issueTitle": "옥주현",
      "issueKey": "옥주현",
      "title": "옥주현",
      "representativeTitle": "옥주현, 한남더힐 100평집 190억원에 매입 “생애 첫 내집”"
    },
    {
      "issueTitle": "김민경",
      "issueKey": "김민경",
      "title": "김민경",
      "representativeTitle": "‘45세’ 미코 출신 김민경 임신 소식… “이 나이에 임밍아웃”"
    },
    {
      "issueTitle": "피아노맨",
      "issueKey": "피아노맨",
      "title": "피아노맨",
      "representativeTitle": "피아노맨, 오늘 '2년 교제' 비연예인과 결혼"
    },
    {
      "issueTitle": "조명우",
      "issueKey": "조명우",
      "title": "조명우",
      "representativeTitle": "‘세계1위’ 조명우 보고타3쿠션월드컵 악연 끊었다…타이홍치엠 꺾고 4강 진출, 타스데미르와 결승行 다퉈"
    },
    {
      "issueTitle": "신동엽",
      "issueKey": "신동엽",
      "title": "신동엽",
      "representativeTitle": "신동엽, 이경실·조혜련에 고급 도시락 플렉스 “옛날에 밥 많이 얻어먹어”"
    },
    {
      "issueTitle": "전유진",
      "issueKey": "전유진",
      "title": "전유진",
      "representativeTitle": "'트롯퀸' 전유진, '전국노래자랑' 경북 의성군 편 축하공연"
    },
    {
      "issueTitle": "박성한",
      "issueKey": "박성한",
      "title": "박성한",
      "representativeTitle": "[포토] 3타수 3안타 박성한, 뜨겁다 뜨거워"
    },
    {
      "issueTitle": "변우석",
      "issueKey": "변우석",
      "title": "변우석",
      "representativeTitle": "모델료 20만원서 수십억 몸값으로…변우석이 증명한 ‘가장 비싼 영수증’"
    },
    {
      "issueTitle": "모든 선박",
      "issueKey": "모든 선박",
      "title": "모든 선박",
      "representativeTitle": "[속보] 카타르 , 12일 부터 모든 선박의 완전한 항해 재개 선언… 종류 불문"
    }
  ]
}