{
  "tab": "game",
  "type": "free-games-and-issues",
  "source": "Epic Games Store + Ruliweb BEST 뉴스 + Inven 주요뉴스",
  "sourceMode": "official-store-api+html",
  "lastUpdatedAt": "2026-04-14T18:48:48.133Z",
  "title": "에픽게임즈 이주의 무료게임",
  "description": "Epic Games Store KR 무료 배포와 루리웹·인벤 인기 게임 이슈를 함께 보여줍니다.",
  "sourceUrl": "https://store.epicgames.com/ko/free-games",
  "itemCount": 2,
  "offers": [
    {
      "id": "9f67865fcf0749a58f4d35827473266f",
      "title": "토막: 지구를 지켜라 리제네레이션",
      "seller": "NETMARBLE MONSTER",
      "url": "https://store.epicgames.com/ko/p/tomak-save-the-earth-regeneration-c1207c",
      "imageUrl": "https://cdn1.epicgames.com/spt-assets/603c0097f96047c38bc199331b5cf95b/tomak--save-the-earth-regeneration-l1n5k.png",
      "originalPriceLabel": "₩9,200",
      "freeUntil": "2026-04-16T15:00:00.000Z"
    },
    {
      "id": "bc9b3091841840ad974ff525873d48c1",
      "title": "Prop Sumo",
      "seller": "Barrel Roll Games GmbH & Co. KG",
      "url": "https://store.epicgames.com/ko/p/propsumo-ca8bd7",
      "imageUrl": "https://cdn1.epicgames.com/spt-assets/a965174568cb492ca3ebbe7a95886261/propsumo-jc5go.png",
      "originalPriceLabel": "₩10,200",
      "freeUntil": "2026-04-16T15:00:00.000Z"
    }
  ],
  "issues": {
    "ruliweb": {
      "label": "루리웹 BEST 뉴스",
      "source": "Ruliweb BEST 뉴스",
      "sourceUrl": "https://bbs.ruliweb.com/best",
      "items": [
        {
          "title": "하운드13, '드래곤소드 : 어웨이크닝' 스팀 페이지 및 7월 발매 공개",
          "url": "https://bbs.ruliweb.com/news/read/223350",
          "meta": "댓글 60"
        },
        {
          "title": "익숙함을 깨는 힘, ‘니케’가 여전히 기대되는 이유 — 정재성·주종현 디렉터 인터뷰",
          "url": "https://bbs.ruliweb.com/news/read/223198",
          "meta": "댓글 41"
        },
        {
          "title": "몬스터와 함께 DIVE, '몬길 : 스타 다이브' 첫 번째 쇼케이스",
          "url": "https://bbs.ruliweb.com/news/read/223241",
          "meta": "댓글 26"
        },
        {
          "title": "이제 타지에서도 굶지마! - '돈 스타브 엘스웨어' 공개",
          "url": "https://bbs.ruliweb.com/news/read/223307",
          "meta": "댓글 0"
        },
        {
          "title": "엑스엘게임즈, ‘더 큐브, 세이브 어스’ 서비스 종료",
          "url": "https://bbs.ruliweb.com/news/read/223243",
          "meta": "댓글 21"
        }
      ]
    },
    "inven": {
      "label": "인벤 주요뉴스",
      "source": "Inven 주요뉴스",
      "sourceUrl": "https://www.inven.co.kr/webzine/news/?hotnews=1",
      "items": [
        {
          "title": "우승 노리는 조일장 \"심리전, 과감함이 더 필요\"",
          "url": "https://www.inven.co.kr/webzine/news/?news=315415",
          "meta": "스타크래프트 · 5시간 전"
        },
        {
          "title": "토스 킬러 조일장, '프황' 정윤종 잡고 2위",
          "url": "https://www.inven.co.kr/webzine/news/?news=315414",
          "meta": "스타크래프트 · 5시간 전"
        },
        {
          "title": "B조 1위 장윤철 \"8강은 테란과 만나고 싶어\"",
          "url": "https://www.inven.co.kr/webzine/news/?news=315413",
          "meta": "스타크래프트 · 6시간 전"
        },
        {
          "title": "우승 후보 장윤철, 조 1위로 8강 진출",
          "url": "https://www.inven.co.kr/webzine/news/?news=315412",
          "meta": "스타크래프트 · 7시간 전"
        },
        {
          "title": "SMG홀딩스X마파(MAPPA), 국내 최초 ‘체인소 맨’ 단독 팝업 개최",
          "url": "https://www.inven.co.kr/webzine/news/?news=315406",
          "meta": "10시간 전"
        }
      ]
    }
  },
  "fetchedSources": [
    {
      "key": "epic-free-games",
      "source": "Epic Games Store",
      "ok": true,
      "itemCount": 2
    },
    {
      "key": "ruliweb-issues",
      "source": "Ruliweb BEST 뉴스",
      "ok": true,
      "itemCount": 5
    },
    {
      "key": "inven-issues",
      "source": "Inven 주요뉴스",
      "ok": true,
      "itemCount": 5
    }
  ]
}
